floulib/Any.py
floulib/Defuzzify.py
floulib/Discrete.py
floulib/DistToPi.py
floulib/DistToPiMultilinear.py
floulib/Fuzzify.py
floulib/LR.py
floulib/Multilinear.py
floulib/Operator.py
floulib/Plot.py
floulib/Rectangle.py
floulib/Rule.py
floulib/Rules.py
floulib/Singleton.py
floulib/Smiley.py
floulib/Term.py
floulib/Terms.py
floulib/Trapezoid.py
floulib/Triangle.py
floulib/Variable.py
floulib/__init__.py
floulib-0.0.2.dist-info/METADATA
floulib-0.0.2.dist-info/WHEEL
floulib-0.0.2.dist-info/licenses/LICENSE
floulib-0.0.2.dist-info/RECORD
