Metadata-Version: 2.1
Name: floulib
Version: 0.0.2
Summary: A package for Fuzzy Logic
Project-URL: Documentation, https://floulib.readthedocs.io/
Project-URL: Homepage, https://github.com/YolfTypo3/floulib
Project-URL: Bug Tracker, https://github.com/YolfTypo3/floulib/issues
Author-email: Laurent Foulloy <yolf.typo3@orange.fr>
Maintainer-email: Laurent Foulloy <yolf.typo3@orange.fr>
License-File: LICENSE
Classifier: License :: OSI Approved :: MIT License
Classifier: Operating System :: OS Independent
Classifier: Programming Language :: Python :: 3
Requires-Python: >=3.7
Requires-Dist: matplotlib
Requires-Dist: numpy
Requires-Dist: scipy
Requires-Dist: shapely
